[[{"age":"12","health":"in great health","gender":"male","income level":"low","number of dependents":"0","survival without jacket":"31%","survival with jacket":"48%"},{"age":"18","health":"in great health","gender":"male","income level":"mid","number of dependents":"1","survival without jacket":"39%","survival with jacket":"54%"},{"age":"18","health":"moderate health problems","gender":"female","income level":"mid","number of dependents":"2","survival without jacket":"13%","survival with jacket":"44%"}]
]